{
    "welcome": "Доброе утро, Елена!",
    "avatar": "https://i.ibb.co/zFgmcFx/avatar.png",
    "hint": "Поиск продуктов",
    "sections": [
        {
            "oid": 1,
            "type": "storiesBlock",
            "items": [
                {
                    "oid": 1,
                    "title": "Тема сторис",
                    "image": "https://i.ibb.co/D8zX154/Rectangle-7.png",
                    "viewed": true,
                    "gradient": {
                        "startColor": "#E58F8D",
                        "endColor": "#CD6541"
                    },
                    "screens": [
                        {
                            "image": "https://images.unsplash.com/photo-1542282088-fe8426682b8f",
                            "title": "Audi first",
                            "description": "Description 1"
                        },
                        {
                            "image": "https://images.unsplash.com/photo-1517524008697-84bbe3c3fd98",
                            "title": "Audi second",
                            "description": "Description 2"
                        }
                    ]
                },
                {
                    "oid": 2,
                    "title": "Тема сторис",
                    "image": "https://i.ibb.co/Lzq0K0w/Rectangle-7-3.png",
                    "viewed": false,
                    "screens": [
                        {
                            "image": "https://images.unsplash.com/photo-1552321876-ac707a080f1b",
                            "title": "BMW",
                            "description": "Description"
                        },
                        {
                            "image": "https://images.unsplash.com/photo-1544986342-f4f2e11b7c02",
                            "title": "BMW 2",
                            "description": "Descriptionn"
                        },
                        {
                            "image": "https://images.unsplash.com/photo-1542906042-f41e62496963",
                            "title": "BMW 3",
                            "description": "Descriptionnn"
                        },
                        {
                            "image": "https://images.unsplash.com/photo-1591117728047-2dc00780492c",
                            "title": "BMW 4",
                            "description": "Descriptionnnn"
                        }
                    ]
                },
                {
                    "oid": 3,
                    "title": "Тема сторис",
                    "image": "https://i.ibb.co/YR1gvTB/Rectangle-7-2.png",
                    "viewed": true,
                    "gradient": {
                        "startColor": "#C3799B",
                        "endColor": "#7292CB"
                    },
                    "screens": [
                        {
                            "image": "https://i.ibb.co/CMnDXbQ/003bd322-5401-4ea5-9da9-d6521c5fb0b2-1.webp",
                            "title": "Mercedes",
                            "description": "Description"
                        },
                        {
                            "image": "https://images.unsplash.com/photo-1570733577524-3a047079e80d",
                            "title": "Mercedes 2",
                            "description": "Descriptionn"
                        },
                        {
                            "image": "https://images.unsplash.com/photo-1514316454349-750a7fd3da3a",
                            "title": "Mercedes 3",
                            "description": "Descriptionnn"
                        }
                    ]
                }
            ]
        },
        {
            "oid": 2,
            "type": "ordersBlock",
            "title": "Ваши заказы",
            "items": [
                {
                    "oid": 281694020042766,
                    "title": "Доставка сегодня с 9:00 до 12:00",
                    "description": "3 позиции, 3.4 кг",
                    "price": 3500,
                    "badge": {
                        "title": "У курьера",
                        "colorBG": "#78BCD9",
                        "colorTxt": "#FFFFFF"
                    },
                    "items": [
                        {
                            "oid": 1,
                            "image": "https://i.ibb.co/Y2y9ZNg/9ae06f46c6a74be035040f131fcfdf09.png"
                        },
                        {
                            "oid": 2,
                            "image": "https://i.ibb.co/x5zhLMJ/9178a6293446509b6e3e67cc8808b832.png"
                        },
                        {
                            "oid": 3,
                            "image": "https://i.ibb.co/Y2y9ZNg/9ae06f46c6a74be035040f131fcfdf09.png"
                        },
                        {
                            "oid": 4,
                            "image": "https://i.ibb.co/x5zhLMJ/9178a6293446509b6e3e67cc8808b832.png"
                        },
                        {
                            "oid": 5,
                            "image": "https://i.ibb.co/Y2y9ZNg/9ae06f46c6a74be035040f131fcfdf09.png"
                        },
                        {
                            "oid": 6,
                            "image": "https://i.ibb.co/x5zhLMJ/9178a6293446509b6e3e67cc8808b832.png"
                        },
                        {
                            "oid": 7,
                            "image": "https://i.ibb.co/Y2y9ZNg/9ae06f46c6a74be035040f131fcfdf09.png"
                        },
                        {
                            "oid": 8,
                            "image": "https://i.ibb.co/x5zhLMJ/9178a6293446509b6e3e67cc8808b832.png"
                        },
                        {
                            "oid": 9,
                            "image": "https://i.ibb.co/Y2y9ZNg/9ae06f46c6a74be035040f131fcfdf09.png"
                        },
                        {
                            "oid": 10,
                            "image": "https://i.ibb.co/x5zhLMJ/9178a6293446509b6e3e67cc8808b832.png"
                        }
                    ]
                },
                {
                    "oid": 281694020042766,
                    "title": "Доставка сегодня с 9:00 до 12:00",
                    "subtitle": "3 позиции, 3.4 кг",
                    "price": 3500,
                    "badge": {
                        "title": "У курьера",
                        "colorBG": "#78BCD9",
                        "colorTxt": "#FFFFFF"
                    },
                    "items": [
                        {
                            "oid": 1,
                            "image": "https://i.ibb.co/Y2y9ZNg/9ae06f46c6a74be035040f131fcfdf09.png"
                        },
                        {
                            "oid": 2,
                            "image": "https://i.ibb.co/x5zhLMJ/9178a6293446509b6e3e67cc8808b832.png"
                        },
                        {
                            "oid": 3,
                            "image": "https://i.ibb.co/Y2y9ZNg/9ae06f46c6a74be035040f131fcfdf09.png"
                        },
                        {
                            "oid": 4,
                            "image": "https://i.ibb.co/x5zhLMJ/9178a6293446509b6e3e67cc8808b832.png"
                        },
                        {
                            "oid": 5,
                            "image": "https://i.ibb.co/Y2y9ZNg/9ae06f46c6a74be035040f131fcfdf09.png"
                        },
                        {
                            "oid": 6,
                            "image": "https://i.ibb.co/x5zhLMJ/9178a6293446509b6e3e67cc8808b832.png"
                        },
                        {
                            "oid": 7,
                            "image": "https://i.ibb.co/Y2y9ZNg/9ae06f46c6a74be035040f131fcfdf09.png"
                        },
                        {
                            "oid": 8,
                            "image": "https://i.ibb.co/x5zhLMJ/9178a6293446509b6e3e67cc8808b832.png"
                        },
                        {
                            "oid": 9,
                            "image": "https://i.ibb.co/Y2y9ZNg/9ae06f46c6a74be035040f131fcfdf09.png"
                        },
                        {
                            "oid": 10,
                            "image": "https://i.ibb.co/x5zhLMJ/9178a6293446509b6e3e67cc8808b832.png"
                        }
                    ]
                }
            ]
        },
        {
            "oid": 3,
            "type": "bannerBlock",
            "title": "Новая акция\n“Двойные зёрна”",
            "titleColor": "#FFFFFF",
            "descriptionColor": "#FFFFFF",
            "description": "Оформляйте заказ с доставкой на воскресенье и получайте зёрна в двойном объёме",
            "image": "https://i.ibb.co/dPHy85k/bg.png",
            "button": {
                "title": "Подробнее",
                "colorBG": "#FFFFFF",
                "colorTxt": "#252423",
                "action": {
                    "path": "constant",
                    "params": [
                        {
                            "key": "oid",
                            "value": 123
                        }
                    ]
                }
            }
        },
        {
            "oid": 4,
            "type": "goodsCarousel",
            "title": "ТОП 5 товаров недели",
            "items": [
                {
                    "oid": 1,
                    "image": "https://i.ibb.co/Y2y9ZNg/9ae06f46c6a74be035040f131fcfdf09.png",
                    "title": "Вареники с картофелем и грибами",
                    "description": "постные, на развес",
                    "price": 74,
                    "oldPrice": 105,
                    "costPer": "за 100 грамм",
                    "promo": "акция -20%",
                    "labels": [
                        "pertnership",
                        "eco",
                        "steam"
                    ]
                },
                {
                    "oid": 2,
                    "image": "https://i.ibb.co/x5zhLMJ/9178a6293446509b6e3e67cc8808b832.png",
                    "title": "Сыр Качотта",
                    "description": "постные, на развес",
                    "price": 120,
                    "costPer": "за 100 грамм",
                    "labels": [
                        "eco"
                    ]
                },
                {
                    "oid": 3,
                    "image": "https://i.ibb.co/Y2y9ZNg/9ae06f46c6a74be035040f131fcfdf09.png",
                    "title": "Вареники с картофелем и грибами",
                    "description": "постные, на развес",
                    "price": 74,
                    "oldPrice": 105,
                    "costPer": "за 100 грамм",
                    "promo": "акция -20%",
                    "labels": [
                        "pertnership",
                        "eco",
                        "steam"
                    ]
                }
            ]
        },
        {
            "oid": 5,
            "type": "bannerBlockNearest",
            "title": "Рядом магазин и кафе «М2 Органик Клуб»",
            "titleColor": "#FFFFFF",
            "descriptionColor": "#FFFFFF",
            "backgroundColor": "#252423",
            "description": "Открыт сегодня до 23:00",
            "image": "https://i.ibb.co/JFBjgn5/avatar.png",
            "distance": "500 метров от вас, 3 мин",
            "action": {
                "path": "constant",
                "params": [
                    {
                        "key": "oid",
                        "value": 123
                    }
                ]
            }
        },
        {
            "oid": 6,
            "type": "goodsCarousel",
            "title": "Товары со скидкой",
            "items": [
                {
                    "oid": 1,
                    "image": "https://i.ibb.co/Y2y9ZNg/9ae06f46c6a74be035040f131fcfdf09.png",
                    "title": "Вареники с картофелем и грибами",
                    "description": "постные, на развес",
                    "price": 74,
                    "oldPrice": 105,
                    "costPer": "за 100 грамм",
                    "promo": "акция -20%",
                    "labels": [
                        "pertnership",
                        "eco",
                        "steam"
                    ]
                },
                {
                    "oid": 2,
                    "image": "https://i.ibb.co/x5zhLMJ/9178a6293446509b6e3e67cc8808b832.png",
                    "title": "Сыр Качотта",
                    "description": "постные, на развес",
                    "price": 120,
                    "oldPrice": 145,
                    "costPer": "за 100 грамм",
                    "labels": [
                        "eco"
                    ]
                },
                {
                    "oid": 3,
                    "image": "https://i.ibb.co/Y2y9ZNg/9ae06f46c6a74be035040f131fcfdf09.png",
                    "title": "Вареники с картофелем и грибами",
                    "description": "постные, на развес",
                    "price": 74,
                    "oldPrice": 105,
                    "costPer": "за 100 грамм",
                    "promo": "акция -20%",
                    "labels": [
                        "pertnership",
                        "eco",
                        "steam"
                    ]
                }
            ]
        },
        {
            "oid": 7,
            "type": "bannerBlock",
            "title": "Дикая рыба северных широт",
            "titleColor": "#FFFFFF",
            "descriptionColor": "#FFFFFF",
            "description": "Порадуйте себя вкусными дарами российских морей и рек",
            "image": "https://i.ibb.co/txdwf6M/bg.png",
            "button": {
                "title": "Подробнее",
                "colorBG": "#FFFFFF",
                "colorTxt": "#252423",
                "action": {
                    "path": "constant",
                    "params": [
                        {
                            "key": "oid",
                            "value": 123
                        },
                        {
                            "key": "oid_category",
                            "value": 456
                        }
                    ]
                }
            }
        },
        {
            "oid": 8,
            "type": "brands",
            "title": "Наши бренды",
            "items": [
                {
                    "oid": 1,
                    "image": "https://i.ibb.co/MpLxbTM/08399cd454035983cce4e7a70072e097.png"
                },
                {
                    "oid": 2,
                    "image": "https://i.ibb.co/GvJqjyP/ed415cbf63d58acc096a9a2eea67a398.png"
                },
                {
                    "oid": 3,
                    "image": "https://i.ibb.co/MpLxbTM/08399cd454035983cce4e7a70072e097.png"
                },
                {
                    "oid": 4,
                    "image": "https://i.ibb.co/GvJqjyP/ed415cbf63d58acc096a9a2eea67a398.png"
                },
                {
                    "oid": 5,
                    "image": "https://i.ibb.co/MpLxbTM/08399cd454035983cce4e7a70072e097.png"
                },
                {
                    "oid": 6,
                    "image": "https://i.ibb.co/GvJqjyP/ed415cbf63d58acc096a9a2eea67a398.png"
                }
            ]
        },
        {
            "oid": 9,
            "type": "popularCategories",
            "title": "Популярные категории",
            "items": [
                {
                    "oid": 123,
                    "image": "https://i.ibb.co/wKPcZtj/Mask-Group.png",
                    "title": "Молоко"
                },
                {
                    "oid": 456,
                    "image": "https://i.ibb.co/6RLjLqb/Mask-Group-2.png",
                    "title": "Йогурты"
                },
                {
                    "oid": 789,
                    "image": "https://i.ibb.co/M2qqxK3/Mask-Group-3.png",
                    "title": "Свинина"
                },
                {
                    "oid": 101,
                    "image": "https://i.ibb.co/LgwZyQ9/Mask-Group.png",
                    "title": "Мягкие и творожные сыры"
                }
            ]
        },
        {
            "oid": 10,
            "type": "goodsCarousel",
            "title": "Новинки от BioGourmet",
            "items": [
                {
                    "oid": 1,
                    "image": "https://i.ibb.co/Y2y9ZNg/9ae06f46c6a74be035040f131fcfdf09.png",
                    "title": "Вареники с картофелем и грибами",
                    "description": "постные, на развес",
                    "price": 74,
                    "oldPrice": 105,
                    "costPer": "за 100 грамм",
                    "promo": "акция -20%",
                    "labels": [
                        "pertnership",
                        "eco",
                        "steam"
                    ]
                },
                {
                    "oid": 2,
                    "image": "https://i.ibb.co/x5zhLMJ/9178a6293446509b6e3e67cc8808b832.png",
                    "title": "Сыр Качотта",
                    "description": "с грибами, на развес",
                    "price": 120,
                    "oldPrice": 145,
                    "costPer": "за 100 грамм",
                    "labels": [
                        "eco"
                    ]
                },
                {
                    "oid": 3,
                    "image": "https://i.ibb.co/Y2y9ZNg/9ae06f46c6a74be035040f131fcfdf09.png",
                    "title": "Вареники с картофелем и грибами",
                    "description": "постные, на развес",
                    "price": 74,
                    "oldPrice": 105,
                    "costPer": "за 100 грамм",
                    "promo": "акция -20%",
                    "labels": [
                        "pertnership",
                        "eco",
                        "steam"
                    ]
                }
            ]
        },
        {
            "oid": 11,
            "type": "ordersBlock",
            "title": "Не заказывали подписки больше 3-х недель",
            "items": [
                {
                    "oid": 1,
                    "title": "Доставка сегодня с 9:00 до 12:00",
                    "description": "3 позиции, 3.4 кг",
                    "price": 3500,
                    "button": {
                        "title": "Заказать",
                        "colorBG": "#7FAA11",
                        "colorTxt": "#FFFFFF",
                        "action": {
                            "path": "constant",
                            "params": [
                                {
                                    "key": "oid",
                                    "value": 123
                                },
                                {
                                    "key": "oid_category",
                                    "value": 456
                                }
                            ]
                        }
                    },
                    "items": [
                        {
                            "oid": 1,
                            "image": "https://i.ibb.co/Y2y9ZNg/9ae06f46c6a74be035040f131fcfdf09.png"
                        },
                        {
                            "oid": 2,
                            "image": "https://i.ibb.co/x5zhLMJ/9178a6293446509b6e3e67cc8808b832.png"
                        },
                        {
                            "oid": 3,
                            "image": "https://i.ibb.co/Y2y9ZNg/9ae06f46c6a74be035040f131fcfdf09.png"
                        },
                        {
                            "oid": 4,
                            "image": "https://i.ibb.co/x5zhLMJ/9178a6293446509b6e3e67cc8808b832.png"
                        },
                        {
                            "oid": 5,
                            "image": "https://i.ibb.co/Y2y9ZNg/9ae06f46c6a74be035040f131fcfdf09.png"
                        },
                        {
                            "oid": 6,
                            "image": "https://i.ibb.co/x5zhLMJ/9178a6293446509b6e3e67cc8808b832.png"
                        },
                        {
                            "oid": 7,
                            "image": "https://i.ibb.co/Y2y9ZNg/9ae06f46c6a74be035040f131fcfdf09.png"
                        },
                        {
                            "oid": 8,
                            "image": "https://i.ibb.co/x5zhLMJ/9178a6293446509b6e3e67cc8808b832.png"
                        },
                        {
                            "oid": 9,
                            "image": "https://i.ibb.co/Y2y9ZNg/9ae06f46c6a74be035040f131fcfdf09.png"
                        },
                        {
                            "oid": 10,
                            "image": "https://i.ibb.co/x5zhLMJ/9178a6293446509b6e3e67cc8808b832.png"
                        }
                    ]
                },
                {
                    "oid": 2,
                    "title": "Доставка сегодня с 9:00 до 12:00",
                    "description": "3 позиции, 3.4 кг",
                    "price": 3500,
                    "button": {
                        "title": "Заказать",
                        "colorBG": "#7FAA11",
                        "colorTxt": "#FFFFFF",
                        "action": {
                            "path": "constant",
                            "params": [
                                {
                                    "key": "oid",
                                    "value": 123
                                },
                                {
                                    "key": "oid_category",
                                    "value": 456
                                }
                            ]
                        }
                    },
                    "items": [
                        {
                            "oid": 1,
                            "image": "https://i.ibb.co/Y2y9ZNg/9ae06f46c6a74be035040f131fcfdf09.png"
                        },
                        {
                            "oid": 2,
                            "image": "https://i.ibb.co/x5zhLMJ/9178a6293446509b6e3e67cc8808b832.png"
                        },
                        {
                            "oid": 3,
                            "image": "https://i.ibb.co/Y2y9ZNg/9ae06f46c6a74be035040f131fcfdf09.png"
                        },
                        {
                            "oid": 4,
                            "image": "https://i.ibb.co/x5zhLMJ/9178a6293446509b6e3e67cc8808b832.png"
                        },
                        {
                            "oid": 5,
                            "image": "https://i.ibb.co/Y2y9ZNg/9ae06f46c6a74be035040f131fcfdf09.png"
                        },
                        {
                            "oid": 6,
                            "image": "https://i.ibb.co/x5zhLMJ/9178a6293446509b6e3e67cc8808b832.png"
                        },
                        {
                            "oid": 7,
                            "image": "https://i.ibb.co/Y2y9ZNg/9ae06f46c6a74be035040f131fcfdf09.png"
                        },
                        {
                            "oid": 8,
                            "image": "https://i.ibb.co/x5zhLMJ/9178a6293446509b6e3e67cc8808b832.png"
                        },
                        {
                            "oid": 9,
                            "image": "https://i.ibb.co/Y2y9ZNg/9ae06f46c6a74be035040f131fcfdf09.png"
                        },
                        {
                            "oid": 10,
                            "image": "https://i.ibb.co/x5zhLMJ/9178a6293446509b6e3e67cc8808b832.png"
                        }
                    ]
                }
            ]
        },
        {
            "oid": 12,
            "type": "bannerBlockNotification",
            "title": "Узнайте больше об экопродуктах",
            "titleColor": "#252423",
            "button": {
                "title": "Узнать",
                "colorBG": "#FFFFFF",
                "colorTxt": "#252423",
                "action": {
                    "path": "constant",
                    "params": [
                        {
                            "key": "oid",
                            "value": 123
                        },
                        {
                            "key": "oid_category",
                            "value": 456
                        }
                    ]
                }
            }
        },
        {
            "oid": 13,
            "type": "goodsCarousel",
            "title": "Товары в избранном",
            "items": [
                {
                    "oid": 1,
                    "image": "https://i.ibb.co/Y2y9ZNg/9ae06f46c6a74be035040f131fcfdf09.png",
                    "title": "Вареники с картофелем и грибами",
                    "description": "постные, на развес",
                    "price": 74,
                    "oldPrice": 105,
                    "costPer": "за 100 грамм",
                    "promo": "акция -20%",
                    "labels": [
                        "pertnership",
                        "eco",
                        "steam"
                    ]
                },
                {
                    "oid": 2,
                    "image": "https://i.ibb.co/x5zhLMJ/9178a6293446509b6e3e67cc8808b832.png",
                    "title": "Сыр Качотта",
                    "description": "с грибами, на развес",
                    "price": 120,
                    "oldPrice": 145,
                    "costPer": "за 100 грамм",
                    "labels": [
                        "eco"
                    ]
                },
                {
                    "oid": 3,
                    "image": "https://i.ibb.co/Y2y9ZNg/9ae06f46c6a74be035040f131fcfdf09.png",
                    "title": "Вареники с картофелем и грибами",
                    "description": "постные, на развес",
                    "price": 74,
                    "oldPrice": 105,
                    "costPer": "за 100 грамм",
                    "promo": "акция -20%",
                    "labels": [
                        "pertnership",
                        "eco",
                        "steam"
                    ]
                }
            ]
        },
        {
            "oid": 14,
            "type": "bannerBlockCornered",
            "title": "Органическая Ферма М2",
            "titleColor": "#252423",
            "descriptionColor": "#252423",
            "description": "Органическое фермерское хозяйство М2 построено на берегу Рузского водохранилища. Мы никогда не используем гармоны для усиления роста и лактации, антибиотики, ГМО и любые химические компоненты.",
            "image": "https://i.ibb.co/khkT5B9/banner.jpg",
            "button": {
                "title": "На ферму",
                "colorBG": "#FFFFFF",
                "colorTxt": "#252423",
                "action": {
                    "path": "constant",
                    "params": [
                        {
                            "key": "oid",
                            "value": 123
                        },
                        {
                            "key": "oid_category",
                            "value": 456
                        }
                    ]
                }
            }
        },
        {
            "oid": 15,
            "type": "contacts",
            "title": "Контакты",
            "phone": "+7 (495) 025-30-30",
            "schedule": "с 9:00 до 21:00, без выходных",
            "socials": [
                {
                    "type": "instagram",
                    "title": "string",
                    "contact": "https://www.instagram.com/m2organicclub/"
                },
                {
                    "type": "facebook",
                    "title": "string",
                    "contact": "https://www.facebook.com/m2organic.cafe/"
                },
                {
                    "type": "youtube",
                    "title": "string",
                    "contact": "https://www.youtube.com/channel/UCEGsvQ_hOLrlmgnTHNw4bYw"
                }
            ]
        }
    ]
}
